etaml/__init__.py
etaml/calibration.py
etaml/etaml.py
etaml/explainability_tools.py
etaml/exploratory_data_analysis.py
etaml/feature_selection.py
etaml/inference.py
etaml/metrics.py
etaml/preprocessing.py
EtaML-0.0.9.dist-info/LICENSE
EtaML-0.0.9.dist-info/METADATA
EtaML-0.0.9.dist-info/WHEEL
EtaML-0.0.9.dist-info/top_level.txt
EtaML-0.0.9.dist-info/RECORD
